QualtricsAPI/__init__.py
QualtricsAPI/Exceptions/__init__.py
QualtricsAPI/Exceptions/exceptions.py
QualtricsAPI/JSON/__init__.py
QualtricsAPI/JSON/parser.py
QualtricsAPI/Library/__init__.py
QualtricsAPI/Library/messages.py
QualtricsAPI/Setup/__init__.py
QualtricsAPI/Setup/credentials.py
QualtricsAPI/Survey/__init__.py
QualtricsAPI/Survey/distributions.py
QualtricsAPI/Survey/responses.py
QualtricsAPI/Users/__init__.py
QualtricsAPI/Users/surveys.py
QualtricsAPI/XM/__init__.py
QualtricsAPI/XM/mailinglists.py
QualtricsAPI/XM/xmdirectory.py
QualtricsAPI/tests/__init__.py
QualtricsAPI/tests/test.py
QualtricsAPI-0.6.2.dist-info/LICENSE
QualtricsAPI-0.6.2.dist-info/METADATA
QualtricsAPI-0.6.2.dist-info/WHEEL
QualtricsAPI-0.6.2.dist-info/top_level.txt
QualtricsAPI-0.6.2.dist-info/RECORD
