Metadata-Version: 2.1
Name: QualtricsAPI
Version: 0.6.2
Summary: QualtricsAPI is a lightweight Python library for the Qualtrics Web API. 
Home-page: https://github.com/Jaseibert/QualtricsAPI
Author: Jeremy Seibert
Author-email: jaseibert5@gmail.com
License: MIT
Keywords: qualtrics api python research survey
Classifier: Programming Language :: Python :: 3.6
Classifier: Programming Language :: Python :: 3.7
Classifier: Programming Language :: Python :: 3.8
Classifier: Programming Language :: Python :: 3.9
Classifier: Programming Language :: Python :: 3.10
Classifier: Programming Language :: Python :: 3.11
Classifier: License :: OSI Approved :: MIT License
Classifier: Operating System :: OS Independent
License-File: LICENSE
Requires-Dist: pandas
Requires-Dist: numpy
Requires-Dist: requests
Requires-Dist: python-dateutil
